strat_backtest/__init__.py
strat_backtest/config.py
strat_backtest/Graphs/data.png
strat_backtest/backtest/__init__.py
strat_backtest/backtest/custom_strats.py
strat_backtest/backtest/finance_data.py
strat_backtest/backtest/optimize.py
strat_backtest/backtest/strats.py
strat_backtest/data/aapl.csv
strat_backtest/data/amzn.csv
strat_backtest/data/msft.csv
strat_backtest/data/qqq.csv
strat_backtest/graph_colors/stock-dark.mplstyle
strat_backtest/graph_colors/stock-light.mplstyle
strat_backtest/reddit_data/__init__.py
strat_backtest/reddit_data/common_stock.py
strat_backtest/reddit_data/most_common.txt
strat_backtest/reddit_data/tickers.csv
strat_backtest-0.0.3.dist-info/LICENSE
strat_backtest-0.0.3.dist-info/METADATA
strat_backtest-0.0.3.dist-info/WHEEL
strat_backtest-0.0.3.dist-info/top_level.txt
strat_backtest-0.0.3.dist-info/RECORD
