Metadata-Version: 2.1
Name: strat-backtest
Version: 0.0.3
Summary: Financial program that backtests a strategy (custom or predefined) on stock data
Home-page: https://github.com/dhruvsamdani/strat-backtest
Author: Dhruv
Author-email: dsamdani@asu.edu
Project-URL: Bug Tracker, https://github.com/dhruvsamdani/strat-backtest/issues
Classifier: Programming Language :: Python :: 3
Classifier: License :: OSI Approved :: MIT License
Classifier: Operating System :: OS Independent
Requires-Python: >=3.8
License-File: LICENSE
Requires-Dist: numpy
Requires-Dist: pandas
Requires-Dist: yfinance
Requires-Dist: praw
Requires-Dist: pytest
Requires-Dist: matplotlib
